{
"id":80,
"url":"",
"guid":"36DBFCB8DA18EE118C5C32A5A9F17050",
"pagename":"Wu.html",
"datalevel":6,
"dataversion":1,
"ispagetobuild":true,
"name":"",
"lastname":"Wu",
"firstname":"Eden",
"pseudo":"",
"website":"https:\/\/grandruru.blogspot.com",
"descriptions":[
],
"books":[
{
"id":115,
"url":"",
"guid":"90DBFCB8DA18EE118C5C32A5A9F17050",
"pagename":"Delphi-in-depth-DataSnap.html",
"datalevel":8,
"dataversion":1,
"ispagetobuild":true,
"name":"Delphi in depth : DataSnap",
"lang":"cn",
"pubdate":"20200729",
"thumb":""}]}