{
"id":69,
"url":"",
"guid":"C894FCB8DA18EE118C5C32A5A9F17050",
"pagename":"Introduktion-til-Delphi-5.html",
"datalevel":8,
"dataversion":1,
"ispagetobuild":true,
"name":"Introduktion til Delphi 5",
"lang":"dk",
"pubdate":"20000000",
"thumb":"",
"isbn10":"8778433428",
"isbn13":"",
"website":"",
"cover":"",
"cover_100w":"",
"cover_150w":"",
"cover_200w":"",
"cover_300w":"",
"cover_400w":"",
"cover_500w":"",
"cover_100h":"",
"cover_200h":"",
"cover_300h":"",
"cover_400h":"",
"cover_500h":"",
"cover_100x100":"",
"cover_200x200":"",
"cover_300x300":"",
"cover_400x400":"",
"cover_500x500":"",
"cover_130x110":"",
"authors":[
{
"id":55,
"url":"",
"guid":"6E94FCB8DA18EE118C5C32A5A9F17050",
"pagename":"Kim-Krarup-Andersen.html",
"datalevel":6,
"dataversion":1,
"ispagetobuild":true,
"name":""}],
"publishers":[
{
"id":25,
"url":"",
"guid":"646BFDB8DA18EE118C5C32A5A9F17050",
"pagename":"IDG.html",
"datalevel":4,
"dataversion":1,
"ispagetobuild":true,
"label":"IDG"}],
"descriptions":[
{
"guid":"4095FCB8DA18EE118C5C32A5A9F17050",
"pagename":"",
"datalevel":3,
"dataversion":1,
"ispagetobuild":true,
"lang":"dk",
"text":"Med udgangspunkt i Windows' grafiske brugergr\u00E6nseflade, gennemg\u00E5s alle trin i udviklingen af henholdsvis et adressekartotek og et videokartotek i programmeringssproget Delphi. Til Windows-versionerne 95, 98 eller NT"}],
"tocs":[
],
"keywords":[
]}