{
"id":32,
"url":"",
"guid":"E63FFCB8DA18EE118C5C32A5A9F17050",
"pagename":"Delphi-in-Depth-FireDAC.html",
"datalevel":8,
"dataversion":1,
"ispagetobuild":true,
"name":"Delphi in Depth: FireDAC",
"lang":"en",
"pubdate":"20170511",
"thumb":"",
"isbn10":"1546391274",
"isbn13":"9781546391272",
"website":"http:\/\/www.jensendatasystems.com\/firedacbook\/",
"cover":"",
"cover_100w":"",
"cover_150w":"",
"cover_200w":"",
"cover_300w":"",
"cover_400w":"",
"cover_500w":"",
"cover_100h":"",
"cover_200h":"",
"cover_300h":"",
"cover_400h":"",
"cover_500h":"",
"cover_100x100":"",
"cover_200x200":"",
"cover_300x300":"",
"cover_400x400":"",
"cover_500x500":"",
"cover_130x110":"",
"authors":[
{
"id":14,
"url":"",
"guid":"823FFCB8DA18EE118C5C32A5A9F17050",
"pagename":"Cary-Jensen.html",
"datalevel":6,
"dataversion":1,
"ispagetobuild":true,
"name":""}],
"publishers":[
{
"id":12,
"url":"",
"guid":"4A35FDB8DA18EE118C5C32A5A9F17050",
"pagename":"Jensen-Data-Systems.html",
"datalevel":4,
"dataversion":1,
"ispagetobuild":true,
"label":"Jensen Data Systems"}],
"descriptions":[
{
"guid":"7240FCB8DA18EE118C5C32A5A9F17050",
"pagename":"",
"datalevel":3,
"dataversion":1,
"ispagetobuild":true,
"lang":"en",
"text":"Cary Jensen's book, Delphi in Depth: FireDAC:\n\nLearn how to connect to a wide variety of databases\nOptimize your connection configurations\nExplore the world of indexes, searches, and filters\nDiscover the power of persisted datasets\nCreate flexible queries using macros and FireDAC scalar functions\nAchieve blazing performance with Array DML\nMaster the art of cached updates\nAdd sophisticated features using Local SQL"}],
"tocs":[
{
"guid":"AE40FCB8DA18EE118C5C32A5A9F17050",
"pagename":"",
"datalevel":3,
"dataversion":1,
"ispagetobuild":true,
"lang":"en",
"text":"Introduction \nChapter 1: Overview of FireDAC\nChapter 2: Connecting to Data\nChapter 3: Configuring FireDAC\nChapter 4: Basic Data Access\nChapter 5: More Data Access\nChapter 6: Navigating and Editing Data\nChapter 7: Creating Indexes\nChapter 8: Searching Data\nChapter 9: Filtering Data\nChapter 10: Creating and Using Virtual Fields\nChapter 11: Persisting Data\nChapter 12: Understanding FDMemTables\nChapter 13: More FDMemTables: Cloned Cursors and Nested DataSets\nChapter 14: The SQL Command Preprocessor\nChapter 15: Array DML\nChapter 16: Using Cached Updates\nChapter 17: Understanding Local SQL\nAppendix A: Code Download, Database Preparation, and Errata\nIndex"}],
"keywords":[
]}